use_cache/__init__.py
use_cache/backends/__init__.py
use_cache/backends/dynamodb.py
use_cache/backends/inmemory.py
use_cache/backends/memcached.py
use_cache/backends/redis.py
use_cache/coders.py
use_cache/decorators.py
use_cache/integrations/__init__.py
use_cache/integrations/fastapi.py
use_cache/key_builders.py
use_cache/manager.py
use_cache/types.py
use_cache-0.1.0.dist-info/WHEEL
use_cache-0.1.0.dist-info/METADATA
use_cache-0.1.0.dist-info/RECORD
