Metadata-Version: 2.3
Name: use-cache
Version: 0.1.0
Summary: Caching library with multiple backend support
Author: miclon
Author-email: miclon <jcnd@163.com>
Requires-Dist: typing-extensions>=4.1.0
Requires-Dist: redis>=5.0.0 ; extra == 'all'
Requires-Dist: aiomcache>=0.8.2 ; extra == 'all'
Requires-Dist: aiobotocore>=2.13.1 ; extra == 'all'
Requires-Dist: fastapi ; extra == 'all'
Requires-Dist: starlette ; extra == 'all'
Requires-Dist: aiobotocore>=2.13.1 ; extra == 'dynamodb'
Requires-Dist: fastapi ; extra == 'fastapi'
Requires-Dist: starlette ; extra == 'fastapi'
Requires-Dist: aiomcache>=0.8.2 ; extra == 'memcached'
Requires-Dist: redis>=5.0.0 ; extra == 'redis'
Requires-Dist: pytest>=7.0.0 ; extra == 'test'
Requires-Dist: pytest-asyncio>=0.21.0 ; extra == 'test'
Requires-Python: >=3.8
Provides-Extra: all
Provides-Extra: dynamodb
Provides-Extra: fastapi
Provides-Extra: memcached
Provides-Extra: redis
Provides-Extra: test
